development_area/__init__.py
development_area/_shared.py
development_area/dataset_conditioner.py
development_area/dataset_inspector.py
development_area/dataset_visualiser.py
development_area/unittest_datasets.py
diver/__init__.py
diver/_shared.py
diver/dataset_conditioner.py
diver/dataset_inspector.py
diver/dataset_visualiser.py
diver/reviewer/__init__.py
diver/reviewer/evaluate_binary_classifiers.py
diver-0.2.3.dist-info/LICENSE
diver-0.2.3.dist-info/METADATA
diver-0.2.3.dist-info/WHEEL
diver-0.2.3.dist-info/top_level.txt
diver-0.2.3.dist-info/RECORD
