Metadata-Version: 2.1
Name: diver
Version: 0.2.3
Summary: diver is a series of tools to speed up common feature-set investigation, conditioning and encoding for common ML algorithms
Home-page: https://github.com/ClearScore/diver
Author: Tom Walker
Author-email: tom.walker@clearscore.com
License: UNKNOWN
Platform: UNKNOWN
Classifier: Development Status :: 4 - Beta
Classifier: Intended Audience :: Developers
Classifier: Topic :: Software Development :: Build Tools
Classifier: License :: OSI Approved :: MIT License
Requires-Python: >=3.6
Requires-Dist: scikit-learn (>=0.22.2)
Requires-Dist: joblib
